spireslayer/__init__.py
spireslayer/card.py
spireslayer/decks.py
spireslayer/save_editor.py
spireslayer-1.1.0.dist-info/LICENSE-APACHE
spireslayer-1.1.0.dist-info/LICENSE-MIT
spireslayer-1.1.0.dist-info/METADATA
spireslayer-1.1.0.dist-info/WHEEL
spireslayer-1.1.0.dist-info/top_level.txt
spireslayer-1.1.0.dist-info/RECORD
