Metadata-Version: 2.1
Name: spireslayer
Version: 1.1.0
Summary: Save file editor for Slay the Spire
Author-email: Rahmat Nazali Salimi <rahmatnazali95@gmail.com>
Maintainer-email: Rahmat Nazali Salimi <rahmatnazali95@gmail.com>
Project-URL: Homepage, https://github.com/rahmatnazali/spireslayer
Project-URL: Bug Tracker, https://github.com/rahmatnazali/spireslayer/issues
Keywords: slay-the-spire,slay,spire,save,editor
Classifier: Development Status :: 5 - Production/Stable
Classifier: Environment :: Console
Classifier: Intended Audience :: Developers
Classifier: Intended Audience :: Education
Classifier: Intended Audience :: Information Technology
Classifier: Intended Audience :: Science/Research
Classifier: License :: OSI Approved :: Apache Software License
Classifier: License :: OSI Approved :: MIT License
Classifier: Natural Language :: English
Classifier: Operating System :: OS Independent
Classifier: Programming Language :: Python :: 3 :: Only
Classifier: Topic :: Games/Entertainment
Requires-Python: >=3.8.10
License-File: LICENSE-APACHE
License-File: LICENSE-MIT
